sdkms_git_sign_tool/__init__.py
sdkms_git_sign_tool/__main__.py
sdkms_git_sign_tool-0.3.0.dist-info/METADATA
sdkms_git_sign_tool-0.3.0.dist-info/WHEEL
sdkms_git_sign_tool-0.3.0.dist-info/entry_points.txt
sdkms_git_sign_tool-0.3.0.dist-info/top_level.txt
sdkms_git_sign_tool-0.3.0.dist-info/RECORD
