Metadata-Version: 2.1
Name: sdkms-git-sign-tool
Version: 0.3.0
Summary: Fortanix DSM Git Sign Tool
Home-page: https://support.fortanix.com
Author: Fortanix
Author-email: support@fortanix.com
License: Apache-2.0
Keywords: DSM,SDKMS,Fortanix DSM,git,sign-tool
Classifier: Development Status :: 5 - Production/Stable
Classifier: Intended Audience :: Developers
Classifier: Intended Audience :: System Administrators
Classifier: License :: OSI Approved :: Apache Software License
Classifier: Programming Language :: Python :: 2
Classifier: Programming Language :: Python :: 3
Classifier: Topic :: Security :: Cryptography
Requires-Dist: sdkms <5.1.0,>=4.35.0
Requires-Dist: gitpython <4.0.0,>=3.1.44
Requires-Dist: PGPy ~=0.6
Requires-Dist: pyasn1 ~=0.4.8
Requires-Dist: python-dateutil ~=2.9.0
Requires-Dist: cryptography ~=36.0.0
